agntcy/identity/service/v1alpha1/app_pb2.py
agntcy/identity/service/v1alpha1/app_pb2.pyi
agntcy/identity/service/v1alpha1/app_pb2_grpc.py
agntcy/identity/service/v1alpha1/app_service_pb2.py
agntcy/identity/service/v1alpha1/app_service_pb2.pyi
agntcy/identity/service/v1alpha1/app_service_pb2_grpc.py
agntcy/identity/service/v1alpha1/app_service_pb2_grpc.pyi
agntcy/identity/service/v1alpha1/auth_service_pb2.py
agntcy/identity/service/v1alpha1/auth_service_pb2.pyi
agntcy/identity/service/v1alpha1/auth_service_pb2_grpc.py
agntcy/identity/service/v1alpha1/auth_service_pb2_grpc.pyi
agntcy/identity/service/v1alpha1/badge_pb2.py
agntcy/identity/service/v1alpha1/badge_pb2.pyi
agntcy/identity/service/v1alpha1/badge_pb2_grpc.py
agntcy/identity/service/v1alpha1/badge_service_pb2.py
agntcy/identity/service/v1alpha1/badge_service_pb2.pyi
agntcy/identity/service/v1alpha1/badge_service_pb2_grpc.py
agntcy/identity/service/v1alpha1/badge_service_pb2_grpc.pyi
agntcy/identity/service/v1alpha1/device_pb2.py
agntcy/identity/service/v1alpha1/device_pb2.pyi
agntcy/identity/service/v1alpha1/device_pb2_grpc.py
agntcy/identity/service/v1alpha1/device_service_pb2.py
agntcy/identity/service/v1alpha1/device_service_pb2.pyi
agntcy/identity/service/v1alpha1/device_service_pb2_grpc.py
agntcy/identity/service/v1alpha1/device_service_pb2_grpc.pyi
agntcy/identity/service/v1alpha1/iam_pb2.py
agntcy/identity/service/v1alpha1/iam_pb2.pyi
agntcy/identity/service/v1alpha1/iam_pb2_grpc.py
agntcy/identity/service/v1alpha1/openapi_pb2.py
agntcy/identity/service/v1alpha1/openapi_pb2.pyi
agntcy/identity/service/v1alpha1/openapi_pb2_grpc.py
agntcy/identity/service/v1alpha1/openapi_v2_pb2.py
agntcy/identity/service/v1alpha1/openapi_v2_pb2.pyi
agntcy/identity/service/v1alpha1/openapi_v2_pb2_grpc.py
agntcy/identity/service/v1alpha1/pagination_pb2.py
agntcy/identity/service/v1alpha1/pagination_pb2.pyi
agntcy/identity/service/v1alpha1/pagination_pb2_grpc.py
agntcy/identity/service/v1alpha1/policy_pb2.py
agntcy_identity_service_sdk-0.0.9.dist-info/METADATA
agntcy_identity_service_sdk-0.0.9.dist-info/WHEEL
agntcy_identity_service_sdk-0.0.9.dist-info/entry_points.txt
agntcy_identity_service_sdk-0.0.9.dist-info/top_level.txt
agntcy_identity_service_sdk-0.0.9.dist-info/RECORD
