Metadata-Version: 2.4
Name: agntcy-identity-service-sdk
Version: 0.0.9
Summary: AGNTCY Identity Service SDK & CLI for Python
Author-email: Jean Diaconu <jdiaconu@cisco.com>
License-Expression: Apache-2.0
Project-URL: Homepage, https://github.com/agntcy/identity-service/sdk/python
Project-URL: Bug Tracker, https://github.com/agntcy/identity-service/issues
Classifier: Programming Language :: Python :: 3
Requires-Python: >=3.11
Requires-Dist: grpcio
Requires-Dist: grpcio-status
Requires-Dist: googleapis-common-protos
Requires-Dist: protobuf
Requires-Dist: grpcio-tools
Requires-Dist: protoc_gen_openapiv2
Requires-Dist: python-dotenv
Requires-Dist: mcp<2.0.0
Requires-Dist: typer
Requires-Dist: httpx
Requires-Dist: starlette
Requires-Dist: a2a-sdk>=0.2.0
Requires-Dist: types-protobuf
Requires-Dist: types-grpcio
Requires-Dist: types-grpcio-status
Provides-Extra: test
Requires-Dist: pytest; extra == "test"
Requires-Dist: pytest-asyncio; extra == "test"
Provides-Extra: lint
Requires-Dist: pylint; extra == "lint"
Requires-Dist: ruff; extra == "lint"
Requires-Dist: mypy; extra == "lint"
